phloemfinder/__init__.py
phloemfinder/feature_selection_using_ml.py
phloemfinder/metabolome_analysis.py
phloemfinder/phenotype_analysis.py
phloemfinder/utils.py
phloemfinder-0.4.3.dist-info/LICENSE
phloemfinder-0.4.3.dist-info/WHEEL
phloemfinder-0.4.3.dist-info/METADATA
phloemfinder-0.4.3.dist-info/RECORD
