Metadata-Version: 2.1
Name: phloemfinder
Version: 0.4.3
Summary: Find plant metabolites related to whitefly pest resistance
Home-page: https://github.com/BleekerLab/phloemfinder
License: Apache-2.0
Author: Marc Galland
Author-email: m.galland@uva.nl
Requires-Python: >=3.9
Classifier: License :: OSI Approved :: Apache Software License
Classifier: Programming Language :: Python :: 3
Classifier: Programming Language :: Python :: 3.9
Classifier: Programming Language :: Python :: 3.10
Classifier: Programming Language :: Python :: 3.11
Requires-Dist: TPOT (>=0.11.7)
Requires-Dist: numpy (<1.24.0)
Requires-Dist: pandas (>=1.5.1)
Requires-Dist: scikit-learn (>=0.24.1)
Requires-Dist: seaborn (>=0.12.1)
Project-URL: Repository, https://github.com/BleekerLab/phloemfinder
